bdp/__init__.py
bdp/figure.py
bdp/group.py
bdp/latex_server.py
bdp/node.py
bdp/point.py
bdp/render.py
bdp/tikz_node.py
bdp/sphinxext/__init__.py
bdp/sphinxext/bdpfigure.py
bdp-0.2.1.dist-info/METADATA
bdp-0.2.1.dist-info/RECORD
bdp-0.2.1.dist-info/WHEEL
bdp-0.2.1.dist-info/entry_points.txt
bdp-0.2.1.dist-info/top_level.txt
tests/__init__.py
tests/conftest.py
tests/test_block.py
tests/test_element.py
tests/test_figure.py
tests/test_group.py
tests/test_path.py
