Metadata-Version: 2.1
Name: bdp
Version: 0.2.1
Summary: Block Diagrams in Python
Home-page: https://github.com/bogdanvuk/bdp
Author: Bogdan Vukobratovic
Author-email: bogdan.vukobratovic@gmail.com
License: BSD
Download-URL: https://github.com/bogdanvuk/bdp/tarball/0.2
Keywords: Python,TikZ,Block diagram,PDF,PNG,Sphinx
Platform: any
Classifier: Development Status :: 4 - Beta
Classifier: Environment :: Console
Classifier: Intended Audience :: Developers
Classifier: License :: OSI Approved :: BSD License
Classifier: Operating System :: OS Independent
Classifier: Programming Language :: Python :: 3 :: Only
Classifier: Programming Language :: Python :: 3.3
Classifier: Programming Language :: Python :: 3.4
Classifier: Framework :: Sphinx :: Extension
Classifier: Topic :: Documentation
Classifier: Topic :: Utilities
Requires-Dist: pexpect
Requires-Dist: sphinx-argparse
